coastseg/UI_elements.py
coastseg/__init__.py
coastseg/bbox.py
coastseg/classifier.py
coastseg/coastseg_logs.py
coastseg/coastseg_map.py
coastseg/common.py
coastseg/core_utilities.py
coastseg/download_tide_model.py
coastseg/downloads.py
coastseg/exception_handler.py
coastseg/exceptions.py
coastseg/extract_shorelines_widget.py
coastseg/extracted_shoreline.py
coastseg/factory.py
coastseg/feature.py
coastseg/file_utilities.py
coastseg/geodata_processing.py
coastseg/intersections.py
coastseg/map_UI.py
coastseg/merge_utils.py
coastseg/ml.py
coastseg/model_info.py
coastseg/models_UI.py
coastseg/plotting.py
coastseg/roi.py
coastseg/sessions.py
coastseg/settings_UI.py
coastseg/shoreline.py
coastseg/shoreline_extraction_area.py
coastseg/tide_correction.py
coastseg/transects.py
coastseg/upload_feature_widget.py
coastseg/validation.py
coastseg/watchable_slider.py
coastseg/zoo_model.py
coastseg/bounding_boxes/shorelines_bounding_boxes.csv
coastseg/bounding_boxes/transects_bounding_boxes.csv
coastseg/bounding_boxes/usa_shorelines_bounding_boxes.geojson
coastseg/bounding_boxes/world_reference_shorelines_bboxes.geojson
coastseg/classifier_model/coastal_image_classification.py
coastseg/tide_model/__init__.py
coastseg/tide_model/tide_regions_map.geojson
coastseg/transects/Transects_grid_region_0.geojson
coastseg/transects/Transects_grid_region_100.geojson
coastseg/transects/Transects_grid_region_102.geojson
coastseg/transects/Transects_grid_region_103.geojson
coastseg/transects/Transects_grid_region_106.geojson
coastseg/transects/Transects_grid_region_109.geojson
coastseg/transects/Transects_grid_region_110.geojson
coastseg/transects/Transects_grid_region_117.geojson
coastseg/transects/Transects_grid_region_15.geojson
coastseg/transects/Transects_grid_region_16.geojson
coastseg/transects/Transects_grid_region_2.geojson
coastseg/transects/Transects_grid_region_22.geojson
coastseg/transects/Transects_grid_region_23.geojson
coastseg/transects/Transects_grid_region_24.geojson
coastseg-1.7.1.dist-info/METADATA
coastseg-1.7.1.dist-info/WHEEL
coastseg-1.7.1.dist-info/licenses/LICENSE
coastseg-1.7.1.dist-info/RECORD
