Metadata-Version: 2.4
Name: coastseg
Version: 1.7.1
Summary: An interactive python package for satellite derived shoreline workflows
Project-URL: Bug Tracker, https://github.com/SatelliteShorelines/CoastSeg/issues
Project-URL: documentation, https://github.com/SatelliteShorelines/CoastSeg/wiki
Project-URL: homepage, https://github.com/SatelliteShorelines/CoastSeg
Project-URL: repository, https://github.com/SatelliteShorelines/CoastSeg
Author-email:  Sharon Fitzpatrick Batiste <sharon.fitzpatrick23@gmail.com>
License:                     GNU GENERAL PUBLIC LICENSE
License-File: LICENSE
Keywords: coastsat,coastseg
Classifier: License :: OSI Approved :: MIT License
Classifier: Natural Language :: English
Classifier: Operating System :: OS Independent
Classifier: Programming Language :: Python :: 3 :: Only
Classifier: Programming Language :: Python :: 3.10
Classifier: Programming Language :: Python :: 3.11
Classifier: Topic :: Scientific/Engineering :: GIS
Requires-Python: <3.11,>=3.10
Requires-Dist: aiohttp
Requires-Dist: chardet
Requires-Dist: coastsat-package>=0.3.3
Requires-Dist: dask
Requires-Dist: doodleverse-utils>=0.0.35
Requires-Dist: geojson
Requires-Dist: geopandas
Requires-Dist: h5py==3.14
Requires-Dist: jupyterlab>=3.0.0
Requires-Dist: leafmap==0.35
Requires-Dist: nest-asyncio
Requires-Dist: netcdf4
Requires-Dist: numpy==1.23.5
Requires-Dist: pooch
Requires-Dist: protobuf==3.20.3
Requires-Dist: pytmd<2.2.0
Requires-Dist: xarray
Provides-Extra: ml
Requires-Dist: tensorflow==2.12.0; extra == 'ml'
Requires-Dist: transformers<5,>=4.48.3; extra == 'ml'
Provides-Extra: test
Requires-Dist: pytest; extra == 'test'
